Metadata-Version: 2.1
Name: chipgr8
Version: 0.1.4
Summary: Chip 8 Emulation for AI
Home-page: https://awiggs.github.io/chip-gr8/
Author: chipgr8
Author-email: root@ejrbuss.net
License: MIT
Platform: UNKNOWN
Requires-Dist: lazyarray
Requires-Dist: numpy
Requires-Dist: pygame
